Main/top.v
/*%%%%%%%%%%%%%%%%%%%%%%%%%%%%%%%%%%%%%%%%%%%%%%%%%%%%%%%%%%%%%%%%%%%%%%%%%%%%%%
%% Project Name  : RISC V 32 BIT CPU
%% File Name     : top.v
%% Author        : Aayush Gid
%%
%% Description   : This module represents the top-level design of a 32-bit RISC-V CPU.
%%                It integrates various functional blocks, including the instruction fetch,
%%                decode, execute, memory access, and write-back stages.
%%                The design follows a pipelined architecture for optimized performance.
%%
%%                The module ensures synchronous operation with a clock signal and utilizes
%%                a reset signal for initialization. It is structured to support different 
%%                instruction formats and efficiently handle data flow within the processor.
%%
%% Copyright     : © 2025 Aayush Gid. All rights reserved.
%%                Unauthorized copying or distribution of this code, via any medium,
%%                is strictly prohibited.
%%
%%%%%%%%%%%%%%%%%%%%%%%%%%%%%%%%%%%%%%%%%%%%%%%%%%%%%%%%%%%%%%%%%%%%%%%%%%%%%%%%*/

/*%%%%%%%%%%%%%%%%%%%%%%%%%%%%%%%%%%%%%%%%%%%%%%%%%%%%%%%%%%%%%%%%%%%%%%%%%%%%%%
%% Modification / Updation History
%%%%%%%%%%%%%%%%%%%%%%%%%%%%%%%%%%%%%%%%%%%%%%%%%%%%%%%%%%%%%%%%%%%%%%%%%%%%%%%%
%% Date          : 23-02-2025
%% Version       : 1.0
%% Change Desc   : Initial version of the top-level RISC-V CPU design.
%%%%%%%%%%%%%%%%%%%%%%%%%%%%%%%%%%%%%%%%%%%%%%%%%%%%%%%%%%%%%%%%%%%%%%%%%%%%%%%%*/


`timescale 1ns / 1ps

/* verilator lint_off DECLFILENAME */
module Program_counter(clk, reset, PC_in, PC_out);

    input clk;
    input reset;
    input [31:0] PC_in;
    output reg [31:0] PC_out;

    always @(posedge clk or posedge reset)
        begin
            PC_out <= (reset)? 32'h00000000 : PC_in;
        end

endmodule

module PC_Plus_4(PC_in, PC_out);

    input [31:0] PC_in;
    output [31:0] PC_out;

    assign PC_out = PC_in + 4;
endmodule

module Adder(PC_in, Imm_in, Sum);
    input [31:0] PC_in;
    input [31:0] Imm_in;
    output [31:0] Sum;

    assign Sum= PC_in + Imm_in;
endmodule

module AND_Gate(A, B, o_Y);
    input A;
    input B;
    output o_Y;
    assign o_Y = A & B ;
endmodule

module mux(A, B, sel, Y);
    input [31:0] A;
    input [31:0] B;
    input wire sel;
    output [31:0] Y;
    assign Y = (sel) ? B : A ;
endmodule

module Instruction_Memory(clk, reset, PC_in, Instruction_out);
    input clk;
    input reset;
    input [4:0] PC_in;
    output reg [31:0] Instruction_out;
    
    reg [31:0] Memory[31:0];

    initial begin
        $readmemh("instructions.mem", Memory);
    end

    always @(posedge clk or posedge reset) begin
        Instruction_out <= (reset)? 32'h00000000 : Memory[PC_in];
    end
endmodule

module Control(i_Instruction, o_Branch, o_MemRead, o_MemtoReg, o_ALUOp, o_MemWrite, o_ALUSrc, o_RegWrite);
    input [6:0] i_Instruction;
    output reg o_Branch;
    output reg o_MemtoReg;
    output reg [1:0] o_ALUOp;
    output reg o_MemWrite;
    output reg o_ALUSrc;
    output reg o_RegWrite;
    output reg o_MemRead;

    always @(*)
    begin
        case (i_Instruction)
        7'b0110011 :                // Register
            begin
                o_Branch = 1'b0;
                o_MemRead = 1'b0;
                o_MemtoReg = 1'b0;
                o_ALUOp = 2'b10;
                o_MemWrite = 1'b0;
                o_ALUSrc = 1'b0;
                o_RegWrite = 1'b1;
            end
        7'b0000011 :                // Load
            begin
                o_Branch = 1'b0;
                o_MemRead = 1'b1;
                o_MemtoReg = 1'b1;
                o_ALUOp = 2'b00;
                o_MemWrite = 1'b0;
                o_ALUSrc = 1'b1;
                o_RegWrite = 1'b1;
            end
        7'b0100011 :                // Store
            begin
                o_Branch = 1'b0;
                o_MemRead = 1'b0;
                o_MemtoReg = 1'b0;
                o_ALUOp = 2'b00;
                o_MemWrite = 1'b1;
                o_ALUSrc = 1'b1;
                o_RegWrite = 1'b0;
            end
        7'b1100011 :                // Branch
            begin
                o_Branch = 1'b1;
                o_MemRead = 1'b0;
                o_MemtoReg = 1'b0;
                o_ALUOp = 2'b01;
                o_MemWrite = 1'b0;
                o_ALUSrc = 1'b0;
                o_RegWrite = 1'b0;
            end
        7'b0010011 :                // Arithmetic
            begin
                o_Branch = 1'b0;
                o_MemRead = 1'b0;
                o_MemtoReg = 1'b0;
                o_ALUOp = 2'b10;
                o_MemWrite = 1'b0;
                o_ALUSrc = 1'b1;
                o_RegWrite = 1'b1;
            end
        default:
            begin
                o_Branch   = 1'b0;
                o_MemRead  = 1'b0;
                o_MemtoReg = 1'b0;
                o_ALUOp    = 2'b00;
                o_MemWrite = 1'b0;
                o_ALUSrc   = 1'b0;
                o_RegWrite = 1'b0;
            end

    endcase

    end
endmodule

module ImmediateGenerator(i_Instruction, o_Immediate);
    input [31:0] i_Instruction;
    output reg [31:0] o_Immediate;    

    initial begin
        o_Immediate = 32'd0;
    end
    always @(*)
        begin
            case(i_Instruction[6:0])
                // I-type Instructions (Immediate Load, Arithmetic)
                7'b0010011, 7'b0000011: 
                    o_Immediate = {{20{i_Instruction[31]}}, i_Instruction[31:20]};

                // S-type Instructions (Store Operations)
                7'b0100011: 
                    o_Immediate = {{20{i_Instruction[31]}}, i_Instruction[31:25], i_Instruction[11:7]};
                    
                // B-type Instructions (Branch Operations)
                7'b1100011: 
                    o_Immediate = {{20{i_Instruction[31]}}, i_Instruction[7], i_Instruction[30:25], i_Instruction[11:8], 1'b0};
                
                default : o_Immediate = 32'h00000000;
            endcase
        end
endmodule

module ALU_Control(i_Func7, i_Func3, i_ALUOp, o_Operation);
    input i_Func7;
    input [2:0] i_Func3;
    input [1:0] i_ALUOp;
    output reg [3:0] o_Operation;

    always  @(*) begin
        case({i_ALUOp, i_Func7, i_Func3})
            6'b00_0_000: o_Operation = 4'b0010;

            // Branch operations
            6'b01_0_000: o_Operation = 4'b0110; // SUB (for BEQ)
            6'b01_0_001: o_Operation = 4'b0110; // BNE
            6'b01_0_100: o_Operation = 4'b1010; // BLT
            6'b01_0_101: o_Operation = 4'b1011; // BGE
            6'b01_0_110: o_Operation = 4'b1100; // BLTU
            6'b01_0_111: o_Operation = 4'b1101; // BGEU

            // R TYPE INSTRUCTIONS
            6'b10_0_000: o_Operation = 4'b0010; // ADD
            6'b10_1_000: o_Operation = 4'b0110; // SUB
            6'b10_0_111: o_Operation = 4'b0000; // AND
            6'b10_0_110: o_Operation = 4'b0001; // OR
            6'b10_0_100: o_Operation = 4'b1000; // XOR
            6'b10_0_001: o_Operation = 4'b0100; // SLL (Shift Left Logical)
            6'b10_0_101: o_Operation = 4'b0101; // SRL (Shift Right Logical)
            6'b10_1_101: o_Operation = 4'b0111; // SRA (Shift Right Arithmetic)
            6'b10_0_010: o_Operation = 4'b1010; // SLT (Set Less Than)
            6'b10_0_011: o_Operation = 4'b1011; // SLTU (Set Less Than Unsigned)

            // I TYPE INSTRUCTIONS
            6'b11_0_000: o_Operation = 4'b0010; // ADDI
            6'b11_0_111: o_Operation = 4'b0000; // ANDI
            6'b11_0_110: o_Operation = 4'b0001; // ORI
            6'b11_0_100: o_Operation = 4'b1000; // XORI
            6'b11_0_001: o_Operation = 4'b0100; // SLLI (Shift Left Logical Immediate)
            6'b11_0_101: o_Operation = 4'b0101; // SRLI (Shift Right Logical Immediate)
            6'b11_1_101: o_Operation = 4'b0111; // SRAI (Shift Right Arithmetic Immediate)
            6'b11_0_010: o_Operation = 4'b1010; // SLTI (Set Less Than Immediate)
            6'b11_0_011: o_Operation = 4'b1011; // SLTUI (Set Less Than Unsigned Immediate)

            // LOAD and STORE Instructions (Use ADD for address calculation)
            6'b00_0_010: o_Operation = 4'b0010; // LW (Load Word)
            6'b00_0_000: o_Operation = 4'b0010; // LB (Load Byte)
            6'b00_0_100: o_Operation = 4'b0010; // LBU (Load Byte Unsigned)
            6'b00_0_001: o_Operation = 4'b0010; // LH (Load Halfword)
            6'b00_0_101: o_Operation = 4'b0010; // LHU (Load Halfword Unsigned)
            6'b00_0_010: o_Operation = 4'b0010; // SW (Store Word)
            6'b00_0_000: o_Operation = 4'b0010; // SB (Store Byte)
            6'b00_0_001: o_Operation = 4'b0010; // SH (Store Halfword)

            default: o_Operation = 4'b1111;
        endcase
    end
endmodule

module ALU(A, B, i_Operation, o_ALU_Result, o_Zero);
    input [31:0] A;
    input [31:0] B;
    input [3:0] i_Operation;
    output reg [31:0] o_ALU_Result;
    output reg o_Zero;

    always @(*) begin
        case (i_Operation)
            4'b0000 : o_ALU_Result = A & B;   // AND
            4'b0001 : o_ALU_Result = A | B;   // OR
            4'b0010 : o_ALU_Result = A + B;   // ADD
            4'b0100 : o_ALU_Result = A << B;   // SLL (Shift Left Logical)
            4'b0101 : o_ALU_Result = A >> B;   // SRL (Shift Right Logical)
            4'b0110 : o_ALU_Result = A - B;   // SUB
            4'b0111 : o_ALU_Result = $signed(A) >>> B;   // SRA (Shift Right Arithmetic)
            4'b1000 : o_ALU_Result = (A ^ B); // XOR
            4'b1010 : o_ALU_Result = ($signed(A) < $signed(B)) ? 32'h00000001 : 32'h00000000; // SLT
            4'b1011 : o_ALU_Result = (A < B) ? 32'h00000001 : 32'h00000000; // SLTU

            4'b1111 : o_ALU_Result = 32'h00000000; // Zero output
        endcase


        o_Zero = (o_ALU_Result == 32'h00000000) ?  1'b1 : 1'b0;
    end
endmodule

module Data_Memory(i_MemWrite, i_MemRead, i_Address, i_WriteData, o_ReadData, clk);
    input wire clk;
    input wire i_MemWrite;
    input wire i_MemRead;
    input wire [4:0] i_Address;
    input wire [31:0] i_WriteData;
    output reg [31:0] o_ReadData;

    reg [31:0] memory [0:31];

    // Load memory from file
    initial begin
        $readmemh("DataMemory.mem", memory, 0, 31); // Explicit range for compatibility
    end

    // Read Operation (Asynchronous)
    always @(*) begin
        if (i_MemRead)
            o_ReadData = memory[i_Address];
        else
            o_ReadData = 32'h00000000;
    end

    // Write Operation (Synchronous)
    always @(posedge clk) begin
        if (i_MemWrite)
            memory[i_Address] <= i_WriteData;
    end

endmodule




module Register(clk, reset, i_RS1, i_RS2, i_RD1,i_WriteData, i_RegWrite ,o_ReadData1, o_ReadData2);
	input clk;
    input reset;
    input [4:0] i_RS1;
    input [4:0] i_RS2;
    input [4:0] i_RD1;
    input i_RegWrite;
    input [31:0] i_WriteData;
    output  [31:0] o_ReadData1;
    output  [31:0] o_ReadData2;
    // integer k;
    reg [31:0] Reg_Memory[0:31];

    // Read initial register values from register.mem
    initial begin
        $readmemh("register.mem", Reg_Memory);
    end

    assign o_ReadData1 = Reg_Memory[i_RS1];
    assign o_ReadData2 = Reg_Memory[i_RS2];
    
    always @(posedge clk or posedge reset)
    begin        
        if (reset) begin
            // for (k = 0; k < 32; k = k + 1) begin
            //     Reg_Memory[k] <= 32'h00000000; // Reset all registers
            // end
        end
        else if (i_RegWrite && i_RD1 != 5'b00000) begin
            Reg_Memory[i_RD1] <= i_WriteData; // Write data to register
        end
        $writememh("register.mem", Reg_Memory);
    end

    
endmodule
/* verilator lint_on DECLFILENAME */

module top(clk, reset);
    input clk;
    input reset;
    wire [31:0] PC_out, PCPlus4, SumOut, InstructionOut, Mux1Out, Mux2Out, ReadData1Out, ReadData2Out, ImmediateOut, ALUResult, DM_read, Mux3Out;
    wire Branch, MemRead, MemtoReg, MemWrite, ALUSrc, RegWrite, zero, Select;
    wire [1:0] ALUOp ;
    wire [3:0] Control_out ;

    Program_counter PC(.clk(clk), .reset(reset), .PC_in(Mux1Out) , .PC_out(PC_out));
    PC_Plus_4 PC4 (.PC_in(PC_out), .PC_out(PCPlus4));
    Adder Add (.PC_in(PC_out), .Imm_in(ImmediateOut), .Sum(SumOut));
    AND_Gate AND (.A(Branch), .B(zero), .o_Y(Select));
    mux Mux1 (.A(PCPlus4), .B(SumOut), .sel(Select), .Y(Mux1Out));
    Instruction_Memory IM ( .clk(clk), .reset(reset), .PC_in(PC_out[6:2]), .Instruction_out(InstructionOut) );
    Control Control (.i_Instruction(InstructionOut[6:0]), .o_Branch(Branch), .o_MemRead(MemRead), .o_MemtoReg(MemtoReg), .o_ALUOp(ALUOp), .o_MemWrite(MemWrite), .o_ALUSrc(ALUSrc), .o_RegWrite(RegWrite));
    ImmediateGenerator ImmGen ( .i_Instruction(InstructionOut), .o_Immediate(ImmediateOut));
    Register Reg (.clk(clk), .reset(reset), .i_RS1(InstructionOut[19:15]), .i_RS2(InstructionOut[24:20]), .i_RD1(InstructionOut[11:7]), .i_WriteData(Mux3Out), .i_RegWrite(RegWrite), .o_ReadData1(ReadData1Out), .o_ReadData2(ReadData2Out));
    mux Mux2 (.A(ReadData2Out), .B(ImmediateOut), .sel(ALUSrc), .Y(Mux2Out));
    ALU_Control AC (.i_Func7(InstructionOut[30]), .i_Func3(InstructionOut[14:12]), .i_ALUOp(ALUOp), .o_Operation(Control_out));
    ALU ALU2 (.A(ReadData1Out), .B(Mux2Out), .i_Operation(Control_out), .o_ALU_Result(ALUResult), .o_Zero(zero));
    Data_Memory DM (.i_MemWrite(MemWrite), .i_MemRead(MemRead), .i_Address(ALUResult[4:0]), .i_WriteData(ReadData2Out),  .o_ReadData(DM_read) ,.clk(clk));
    mux Mux3 (.A(ALUResult), .B(DM_read), .sel(MemtoReg), .Y(Mux3Out));
    
endmodule

Main/tb_top.v
`timescale 1ns / 1ps

module tb_top();

    // Testbench Signals
    reg clk;
    reg reset;

    // Instantiate the DUT (Device Under Test)
    top uut (
        .clk(clk),
        .reset(reset)
    );

    // Clock Generation (50 MHz => 20ns period)
    always #10 clk = ~clk;

    initial begin
        // Initialize signals
        clk = 0;
        reset = 1;

        // Hold reset for some cycles
        #10;
        reset = 0;

        // Run the simulation for some time
        #600;

        // Finish simulation
        $finish;
    end

    // Dump waveforms for GTKWave
    initial begin
        $dumpfile("waveform.vcd"); // Output waveform file
        $dumpvars(0, tb_top);      // Dump all variables in tb_top
    end

endmodule

Main/waveform.vcd
$date
	Mon Feb 24 22:14:47 2025
$end
$version
	Icarus Verilog
$end
$timescale
	1ps
$end
$scope module tb_top $end
$var reg 1 ! clk $end
$var reg 1 " reset $end
$scope module uut $end
$var wire 1 ! clk $end
$var wire 1 " reset $end
$var wire 1 # zero $end
$var wire 32 $ SumOut [31:0] $end
$var wire 1 % Select $end
$var wire 1 & RegWrite $end
$var wire 32 ' ReadData2Out [31:0] $end
$var wire 32 ( ReadData1Out [31:0] $end
$var wire 32 ) PC_out [31:0] $end
$var wire 32 * PCPlus4 [31:0] $end
$var wire 32 + Mux3Out [31:0] $end
$var wire 32 , Mux2Out [31:0] $end
$var wire 32 - Mux1Out [31:0] $end
$var wire 1 . MemtoReg $end
$var wire 1 / MemWrite $end
$var wire 1 0 MemRead $end
$var wire 32 1 InstructionOut [31:0] $end
$var wire 32 2 ImmediateOut [31:0] $end
$var wire 32 3 DM_read [31:0] $end
$var wire 4 4 Control_out [3:0] $end
$var wire 1 5 Branch $end
$var wire 1 6 ALUSrc $end
$var wire 32 7 ALUResult [31:0] $end
$var wire 2 8 ALUOp [1:0] $end
$scope module AC $end
$var wire 3 9 i_Func3 [2:0] $end
$var wire 1 : i_Func7 $end
$var wire 2 ; i_ALUOp [1:0] $end
$var reg 4 < o_Operation [3:0] $end
$upscope $end
$scope module ALU2 $end
$var wire 4 = i_Operation [3:0] $end
$var wire 32 > B [31:0] $end
$var wire 32 ? A [31:0] $end
$var reg 32 @ o_ALU_Result [31:0] $end
$var reg 1 # o_Zero $end
$upscope $end
$scope module AND $end
$var wire 1 # B $end
$var wire 1 % o_Y $end
$var wire 1 5 A $end
$upscope $end
$scope module Add $end
$var wire 32 A Sum [31:0] $end
$var wire 32 B PC_in [31:0] $end
$var wire 32 C Imm_in [31:0] $end
$upscope $end
$scope module Control $end
$var wire 7 D i_Instruction [6:0] $end
$var reg 2 E o_ALUOp [1:0] $end
$var reg 1 6 o_ALUSrc $end
$var reg 1 5 o_Branch $end
$var reg 1 0 o_MemRead $end
$var reg 1 / o_MemWrite $end
$var reg 1 . o_MemtoReg $end
$var reg 1 & o_RegWrite $end
$upscope $end
$scope module DM $end
$var wire 1 ! clk $end
$var wire 5 F i_Address [4:0] $end
$var wire 1 0 i_MemRead $end
$var wire 1 / i_MemWrite $end
$var wire 32 G i_WriteData [31:0] $end
$var reg 32 H o_ReadData [31:0] $end
$upscope $end
$scope module IM $end
$var wire 5 I PC_in [4:0] $end
$var wire 1 ! clk $end
$var wire 1 " reset $end
$var reg 32 J Instruction_out [31:0] $end
$upscope $end
$scope module ImmGen $end
$var wire 32 K i_Instruction [31:0] $end
$var reg 32 L o_Immediate [31:0] $end
$upscope $end
$scope module Mux1 $end
$var wire 32 M B [31:0] $end
$var wire 1 % sel $end
$var wire 32 N Y [31:0] $end
$var wire 32 O A [31:0] $end
$upscope $end
$scope module Mux2 $end
$var wire 32 P B [31:0] $end
$var wire 1 6 sel $end
$var wire 32 Q Y [31:0] $end
$var wire 32 R A [31:0] $end
$upscope $end
$scope module Mux3 $end
$var wire 32 S A [31:0] $end
$var wire 32 T B [31:0] $end
$var wire 1 . sel $end
$var wire 32 U Y [31:0] $end
$upscope $end
$scope module PC $end
$var wire 32 V PC_in [31:0] $end
$var wire 1 ! clk $end
$var wire 1 " reset $end
$var reg 32 W PC_out [31:0] $end
$upscope $end
$scope module PC4 $end
$var wire 32 X PC_in [31:0] $end
$var wire 32 Y PC_out [31:0] $end
$upscope $end
$scope module Reg $end
$var wire 1 ! clk $end
$var wire 5 Z i_RD1 [4:0] $end
$var wire 5 [ i_RS1 [4:0] $end
$var wire 5 \ i_RS2 [4:0] $end
$var wire 1 & i_RegWrite $end
$var wire 32 ] i_WriteData [31:0] $end
$var wire 32 ^ o_ReadData1 [31:0] $end
$var wire 32 _ o_ReadData2 [31:0] $end
$var wire 1 " reset $end
$upscope $end
$upscope $end
$upscope $end
$enddefinitions $end
#0
$dumpvars
b0 _
b0 ^
b0 ]
b0 \
b0 [
b0 Z
b100 Y
b0 X
b0 W
b100 V
b0 U
b0 T
b0 S
b0 R
b0 Q
b0 P
b100 O
b100 N
b0 M
b0 L
b0 K
b0 J
b0 I
b0 H
b0 G
b0 F
b0 E
b0 D
b0 C
b0 B
b0 A
b0 @
b0 ?
b0 >
b10 =
b10 <
b0 ;
0:
b0 9
b0 8
b0 7
06
05
b10 4
b0 3
b0 2
b0 1
00
0/
0.
b100 -
b0 ,
b0 +
b100 *
b0 )
b0 (
b0 '
0&
0%
b0 $
1#
1"
0!
$end
#10000
b101 +
b101 U
b101 ]
b101 F
0#
b101 7
b101 @
b101 S
b101 ,
b101 >
b101 Q
1&
16
b10 8
b10 ;
b10 E
b101 2
b101 C
b101 L
b101 P
b1 Z
b101 '
b101 G
b101 R
b101 _
b101 \
b10011 D
b1000 -
b1000 N
b1000 V
b1 I
b10100000000000010010011 1
b10100000000000010010011 J
b10100000000000010010011 K
b1000 *
b1000 O
b1000 Y
b1001 $
b1001 A
b1001 M
b100 )
b100 B
b100 W
b100 X
0"
1!
#20000
0!
#30000
b1010 +
b1010 U
b1010 ]
b1010 F
b1010 7
b1010 @
b1010 S
b1010 ,
b1010 >
b1010 Q
b1100 -
b1100 N
b1100 V
b10 I
b1010 2
b1010 C
b1010 L
b1010 P
b10 Z
b1010 '
b1010 G
b1010 R
b1010 _
b1010 \
b1100 *
b1100 O
b1100 Y
b10010 $
b10010 A
b10010 M
b1000 )
b1000 B
b1000 W
b1000 X
b101000000000000100010011 1
b101000000000000100010011 J
b101000000000000100010011 K
1!
#40000
0!
#50000
b101 +
b101 U
b101 ]
b101 F
b101 7
b101 @
b101 S
b101 ,
b101 >
b101 Q
b101 2
b101 C
b101 L
b101 P
b11 Z
b101 '
b101 G
b101 R
b101 _
b101 \
b10000 -
b10000 N
b10000 V
b11 I
b10100000000000110010011 1
b10100000000000110010011 J
b10100000000000110010011 K
b10000 *
b10000 O
b10000 Y
b10001 $
b10001 A
b10001 M
b1100 )
b1100 B
b1100 W
b1100 X
1!
#60000
0!
#70000
b1111 +
b1111 U
b1111 ]
b1111 F
b1111 7
b1111 @
b1111 S
b1111 ,
b1111 >
b1111 Q
b10100 -
b10100 N
b10100 V
b100 I
b1111 2
b1111 C
b1111 L
b1111 P
b100 Z
b1111 '
b1111 G
b1111 R
b1111 _
b1111 \
b10100 *
b10100 O
b10100 Y
b11111 $
b11111 A
b11111 M
b10000 )
b10000 B
b10000 W
b10000 X
b111100000000001000010011 1
b111100000000001000010011 J
b111100000000001000010011 K
1!
#80000
0!
#90000
1%
1#
b0 +
b0 U
b0 ]
b0 F
b110 4
b110 <
b110 =
b101 ,
b101 >
b101 Q
b0 7
b0 @
b0 S
0&
06
b1 8
b1 ;
b1 E
15
b1000 2
b1000 C
b1000 L
b1000 P
b1000 Z
b101 '
b101 G
b101 R
b101 _
b1 \
b101 (
b101 ?
b101 ^
b11 [
b1100011 D
b11100 -
b11100 N
b11100 V
b101 I
b100011000010001100011 1
b100011000010001100011 J
b100011000010001100011 K
b11000 *
b11000 O
b11000 Y
b11100 $
b11100 A
b11100 M
b10100 )
b10100 B
b10100 W
b10100 X
1!
#100000
0!
#110000
0%
b101 +
b101 U
b101 ]
b101 F
0#
b101 7
b101 @
b101 S
b100000 -
b100000 N
b100000 V
b111 I
b1010 (
b1010 ?
b1010 ^
b10 [
b100000 *
b100000 O
b100000 Y
b100100 $
b100100 A
b100100 M
b11100 )
b11100 B
b11100 W
b11100 X
b100010000010001100011 1
b100010000010001100011 J
b100010000010001100011 K
1!
#120000
0!
#130000
1%
b0 +
b0 U
b0 ]
b0 F
1#
b0 7
b0 @
b0 S
b1 9
b101 (
b101 ?
b101 ^
b11 [
b101000 -
b101000 N
b101000 V
b1000 I
b100011001010001100011 1
b100011001010001100011 J
b100011001010001100011 K
b100100 *
b100100 O
b100100 Y
b101000 $
b101000 A
b101000 M
b100000 )
b100000 B
b100000 W
b100000 X
1!
#140000
0!
#150000
1%
b0 +
b0 U
b0 ]
b0 F
b1010 4
b1010 <
b1010 =
1#
b0 7
b0 @
b0 S
b110000 -
b110000 N
b110000 V
b1010 I
b100 9
b1010 (
b1010 ?
b1010 ^
b10 [
b101100 *
b101100 O
b101100 Y
b110000 $
b110000 A
b110000 M
b101000 )
b101000 B
b101000 W
b101000 X
b100010100010001100011 1
b100010100010001100011 J
b100010100010001100011 K
1!
#160000
0!
#170000
b1011 4
b1011 <
b1011 =
b101 9
b111000 -
b111000 N
b111000 V
b1100 I
b100010101010001100011 1
b100010101010001100011 J
b100010101010001100011 K
b110100 *
b110100 O
b110100 Y
b111000 $
b111000 A
b111000 M
b110000 )
b110000 B
b110000 W
b110000 X
1!
#180000
0!
#190000
b1100 4
b1100 <
b1100 =
b1010 ,
b1010 >
b1010 Q
b1000000 -
b1000000 N
b1000000 V
b1110 I
b110 9
b1010 '
b1010 G
b1010 R
b1010 _
b10 \
b101 (
b101 ?
b101 ^
b1 [
b111100 *
b111100 O
b111100 Y
b1000000 $
b1000000 A
b1000000 M
b111000 )
b111000 B
b111000 W
b111000 X
b1000001110010001100011 1
b1000001110010001100011 J
b1000001110010001100011 K
1!
#200000
0!
#210000
b1101 4
b1101 <
b1101 =
b101 ,
b101 >
b101 Q
b111 9
b101 '
b101 G
b101 R
b101 _
b1 \
b1010 (
b1010 ?
b1010 ^
b10 [
b1001000 -
b1001000 N
b1001000 V
b10000 I
b100010111010001100011 1
b100010111010001100011 J
b100010111010001100011 K
b1000100 *
b1000100 O
b1000100 Y
b1001000 $
b1001000 A
b1001000 M
b1000000 )
b1000000 B
b1000000 W
b1000000 X
1!
#220000
0!
#230000
b1001100 -
b1001100 N
b1001100 V
0%
b1111 4
b1111 <
b1111 =
bx ,
bx >
bx Q
b0 8
b0 ;
b0 E
05
b10010 I
b0 2
b0 C
b0 L
b0 P
bx 9
x:
bx Z
bx '
bx G
bx R
bx _
bx \
bx (
bx ?
bx ^
bx [
bx D
b1001100 *
b1001100 O
b1001100 Y
b1001000 $
b1001000 A
b1001000 M
b1001000 )
b1001000 B
b1001000 W
b1001000 X
bx 1
bx J
bx K
1!
#240000
0!
#250000
b1010000 -
b1010000 N
b1010000 V
b10011 I
b1010000 *
b1010000 O
b1010000 Y
b1001100 $
b1001100 A
b1001100 M
b1001100 )
b1001100 B
b1001100 W
b1001100 X
1!
#260000
0!
#270000
b1010100 -
b1010100 N
b1010100 V
b10100 I
b1010100 *
b1010100 O
b1010100 Y
b1010000 $
b1010000 A
b1010000 M
b1010000 )
b1010000 B
b1010000 W
b1010000 X
1!
#280000
0!
#290000
b1011000 -
b1011000 N
b1011000 V
b10101 I
b1011000 *
b1011000 O
b1011000 Y
b1010100 $
b1010100 A
b1010100 M
b1010100 )
b1010100 B
b1010100 W
b1010100 X
1!
#300000
0!
#310000
b1011100 -
b1011100 N
b1011100 V
b10110 I
b1011100 *
b1011100 O
b1011100 Y
b1011000 $
b1011000 A
b1011000 M
b1011000 )
b1011000 B
b1011000 W
b1011000 X
1!
#320000
0!
#330000
b1100000 -
b1100000 N
b1100000 V
b10111 I
b1100000 *
b1100000 O
b1100000 Y
b1011100 $
b1011100 A
b1011100 M
b1011100 )
b1011100 B
b1011100 W
b1011100 X
1!
#340000
0!
#350000
b1100100 -
b1100100 N
b1100100 V
b11000 I
b1100100 *
b1100100 O
b1100100 Y
b1100000 $
b1100000 A
b1100000 M
b1100000 )
b1100000 B
b1100000 W
b1100000 X
1!
#360000
0!
#370000
b1101000 -
b1101000 N
b1101000 V
b11001 I
b1101000 *
b1101000 O
b1101000 Y
b1100100 $
b1100100 A
b1100100 M
b1100100 )
b1100100 B
b1100100 W
b1100100 X
1!
#380000
0!
#390000
b1101100 -
b1101100 N
b1101100 V
b11010 I
b1101100 *
b1101100 O
b1101100 Y
b1101000 $
b1101000 A
b1101000 M
b1101000 )
b1101000 B
b1101000 W
b1101000 X
1!
#400000
0!
#410000
b1110000 -
b1110000 N
b1110000 V
b11011 I
b1110000 *
b1110000 O
b1110000 Y
b1101100 $
b1101100 A
b1101100 M
b1101100 )
b1101100 B
b1101100 W
b1101100 X
1!
#420000
0!
#430000
b1110100 -
b1110100 N
b1110100 V
b11100 I
b1110100 *
b1110100 O
b1110100 Y
b1110000 $
b1110000 A
b1110000 M
b1110000 )
b1110000 B
b1110000 W
b1110000 X
1!
#440000
0!
#450000
b1111000 -
b1111000 N
b1111000 V
b11101 I
b1111000 *
b1111000 O
b1111000 Y
b1110100 $
b1110100 A
b1110100 M
b1110100 )
b1110100 B
b1110100 W
b1110100 X
1!
#460000
0!
#470000
b1111100 -
b1111100 N
b1111100 V
b11110 I
b1111100 *
b1111100 O
b1111100 Y
b1111000 $
b1111000 A
b1111000 M
b1111000 )
b1111000 B
b1111000 W
b1111000 X
1!
#480000
0!
#490000
b10000000 -
b10000000 N
b10000000 V
b11111 I
b10000000 *
b10000000 O
b10000000 Y
b1111100 $
b1111100 A
b1111100 M
b1111100 )
b1111100 B
b1111100 W
b1111100 X
1!
#500000
0!
#510000
b10000100 -
b10000100 N
b10000100 V
b0 I
b10000100 *
b10000100 O
b10000100 Y
b10000000 $
b10000000 A
b10000000 M
b10000000 )
b10000000 B
b10000000 W
b10000000 X
1!
#520000
0!
#530000
b101 +
b101 U
b101 ]
b101 F
0#
b101 7
b101 @
b101 S
b10 4
b10 <
b10 =
b101 ,
b101 >
b101 Q
1&
16
b10 8
b10 ;
b10 E
b101 2
b101 C
b101 L
b101 P
b0 9
0:
b1 Z
b101 '
b101 G
b101 R
b101 _
b101 \
b0 (
b0 ?
b0 ^
b0 [
b10011 D
b10001000 -
b10001000 N
b10001000 V
b1 I
b10100000000000010010011 1
b10100000000000010010011 J
b10100000000000010010011 K
b10001000 *
b10001000 O
b10001000 Y
b10001001 $
b10001001 A
b10001001 M
b10000100 )
b10000100 B
b10000100 W
b10000100 X
1!
#540000
0!
#550000
b1010 +
b1010 U
b1010 ]
b1010 F
b1010 7
b1010 @
b1010 S
b1010 ,
b1010 >
b1010 Q
b10001100 -
b10001100 N
b10001100 V
b10 I
b1010 2
b1010 C
b1010 L
b1010 P
b10 Z
b1010 '
b1010 G
b1010 R
b1010 _
b1010 \
b10001100 *
b10001100 O
b10001100 Y
b10010010 $
b10010010 A
b10010010 M
b10001000 )
b10001000 B
b10001000 W
b10001000 X
b101000000000000100010011 1
b101000000000000100010011 J
b101000000000000100010011 K
1!
#560000
0!
#570000
b101 +
b101 U
b101 ]
b101 F
b101 7
b101 @
b101 S
b101 ,
b101 >
b101 Q
b101 2
b101 C
b101 L
b101 P
b11 Z
b101 '
b101 G
b101 R
b101 _
b101 \
b10010000 -
b10010000 N
b10010000 V
b11 I
b10100000000000110010011 1
b10100000000000110010011 J
b10100000000000110010011 K
b10010000 *
b10010000 O
b10010000 Y
b10010001 $
b10010001 A
b10010001 M
b10001100 )
b10001100 B
b10001100 W
b10001100 X
1!
#580000
0!
#590000
b1111 +
b1111 U
b1111 ]
b1111 F
b1111 7
b1111 @
b1111 S
b1111 ,
b1111 >
b1111 Q
b10010100 -
b10010100 N
b10010100 V
b100 I
b1111 2
b1111 C
b1111 L
b1111 P
b100 Z
b1111 '
b1111 G
b1111 R
b1111 _
b1111 \
b10010100 *
b10010100 O
b10010100 Y
b10011111 $
b10011111 A
b10011111 M
b10010000 )
b10010000 B
b10010000 W
b10010000 X
b111100000000001000010011 1
b111100000000001000010011 J
b111100000000001000010011 K
1!
#600000
0!
