RegisterFile/register_file.v
`timescale 1ns / 1ps

// ----------------------------------------------------
// Module: Register File
// Description: Implements a set of 32 registers (x0 - x31)
//              with two read ports and one write port.
// Author: [Your Name]
// Date: [Date]
// ----------------------------------------------------

module register_file (
    input wire clk,             // Clock signal
    input wire reset,           // Active high reset
    input wire reg_write,       // Write enable signal
    input wire [4:0] rs1,       // Read register 1 address
    input wire [4:0] rs2,       // Read register 2 address
    input wire [4:0] rd,        // Write register address
    input wire [31:0] write_data, // Data to be written
    output wire [31:0] read_data1, // Read data from rs1
    output wire [31:0] read_data2  // Read data from rs2
);

    // 32 registers (x0 - x31) initialized to zero
    reg [31:0] registers [0:31];

    integer i;

    // Read ports (Asynchronous)
    assign read_data1 = registers[rs1];
    assign read_data2 = registers[rs2];

    // Write operation (Synchronous, x0 remains zero)
    always @(posedge clk or posedge reset) begin
        if (reset) begin
            for (i = 0; i < 32; i = i + 1) begin
                registers[i] <= 32'h00000000;  // Reset all registers to 0
            end
        end
        else if (reg_write && rd != 5'b00000) begin
            registers[rd] <= write_data;  // Write data to rd (except x0)
        end
    end

endmodule

RegisterFile/tb_register_file.v
`timescale 1ns / 1ps

// ----------------------------------------------------
// Testbench: Register File
// Description: Verifies register file read/write operations
//              while ensuring x0 remains zero.
// ----------------------------------------------------

module tb_register_file;

    // Testbench Signals
    reg clk;
    reg reset;
    reg reg_write;
    reg [4:0] rs1, rs2, rd;
    reg [31:0] write_data;
    wire [31:0] read_data1, read_data2;

    // Clock Generation (50 MHz = 20ns period)
    always #10 clk = ~clk;

    // Instantiate the Register File
    register_file uut (
        .clk(clk),
        .reset(reset),
        .reg_write(reg_write),
        .rs1(rs1),
        .rs2(rs2),
        .rd(rd),
        .write_data(write_data),
        .read_data1(read_data1),
        .read_data2(read_data2)
    );

    // Test Sequence
    initial begin
        // VCD Waveform Dump Setup
        $dumpfile("dump.vcd");  // Creates the waveform file
        $dumpvars(0, tb_register_file);  // Dumps all signals
        
        // Initialize Signals
        clk = 0;
        reset = 1;
        reg_write = 0;
        rd = 5'b00000;  // No writes initially
        write_data = 32'h00000000;
        rs1 = 5'b00000;
        rs2 = 5'b00000;

        #15 reset = 0;  // Deassert reset
        
        // Write data to register x5
        #10 reg_write = 1; rd = 5'b00101; write_data = 32'hDEADBEEF;
        
        // Write data to register x10
        #20 rd = 5'b01010; write_data = 32'hCAFEBABE;
        
        // Read from x5 and x10
        #20 reg_write = 0; rs1 = 5'b00101; rs2 = 5'b01010;
        
        // Write to register x0 (should remain zero)
        #20 reg_write = 1; rd = 5'b00000; write_data = 32'hFFFFFFFF;
        
        // Read x0 to check it is still zero
        #20 reg_write = 0; rs1 = 5'b00000;
        
        #50 $finish;
    end

    // Monitor Values
    initial begin
        $monitor("Time=%0t | clk=%b | reset=%b | reg_write=%b | rs1=%d, rs2=%d | rd=%d | write_data=%h | read_data1=%h | read_data2=%h", 
                 $time, clk, reset, reg_write, rs1, rs2, rd, write_data, read_data1, read_data2);
    end

endmodule

RegisterFile/dump.vcd
$date
	Sun Feb 09 21:32:47 2025
$end
$version
	Icarus Verilog
$end
$timescale
	1ps
$end
$scope module tb_register_file $end
$var wire 32 ! read_data2 [31:0] $end
$var wire 32 " read_data1 [31:0] $end
$var reg 1 # clk $end
$var reg 5 $ rd [4:0] $end
$var reg 1 % reg_write $end
$var reg 1 & reset $end
$var reg 5 ' rs1 [4:0] $end
$var reg 5 ( rs2 [4:0] $end
$var reg 32 ) write_data [31:0] $end
$scope module uut $end
$var wire 1 # clk $end
$var wire 5 * rd [4:0] $end
$var wire 32 + read_data1 [31:0] $end
$var wire 32 , read_data2 [31:0] $end
$var wire 1 % reg_write $end
$var wire 1 & reset $end
$var wire 5 - rs1 [4:0] $end
$var wire 5 . rs2 [4:0] $end
$var wire 32 / write_data [31:0] $end
$var integer 32 0 i [31:0] $end
$upscope $end
$upscope $end
$enddefinitions $end
#0
$dumpvars
b100000 0
b0 /
b0 .
b0 -
b0 ,
b0 +
b0 *
b0 )
b0 (
b0 '
1&
0%
b0 $
0#
b0 "
b0 !
$end
#10000
b100000 0
1#
#15000
0&
#20000
0#
#25000
b11011110101011011011111011101111 )
b11011110101011011011111011101111 /
b101 $
b101 *
1%
#30000
1#
#40000
0#
#45000
b11001010111111101011101010111110 )
b11001010111111101011101010111110 /
b1010 $
b1010 *
#50000
1#
#60000
0#
#65000
b11001010111111101011101010111110 !
b11001010111111101011101010111110 ,
b1010 (
b1010 .
b11011110101011011011111011101111 "
b11011110101011011011111011101111 +
b101 '
b101 -
0%
#70000
1#
#80000
0#
#85000
b11111111111111111111111111111111 )
b11111111111111111111111111111111 /
b0 $
b0 *
1%
#90000
1#
#100000
0#
#105000
b0 "
b0 +
b0 '
b0 -
0%
