ALUControl/alu_control.v
`timescale 1ns / 1ps

// --------------------------------------------------
// Module: ALU Control
// Description: Determines ALU operation based on 
//              function codes from the instruction
// Author: [Your Name]
// Date: [Date]
// --------------------------------------------------

module alu_control (
    input wire [1:0] alu_op,        // ALU Operation Control from Control Unit
    input wire [3:0] funct,         // Function code from Instruction
    output reg [3:0] alu_control_out // Control signal for ALU
);

// ALU Control Logic
always @(*) begin
    case (alu_op)
        2'b00: alu_control_out = 4'b0010;  // Load/Store (Addition)
        2'b01: alu_control_out = 4'b0110;  // Branch (Subtraction)
        2'b10: begin
            case (funct)
                4'b0000: alu_control_out = 4'b0010;  // ADD
                4'b1000: alu_control_out = 4'b0110;  // SUB
                4'b0111: alu_control_out = 4'b0000;  // AND
                4'b0110: alu_control_out = 4'b0001;  // OR
                4'b0100: alu_control_out = 4'b1100;  // XOR
                default: alu_control_out = 4'b1111;  // Invalid Operation
            endcase
        end
        default: alu_control_out = 4'b1111; // Default case (Invalid)
    endcase
end

endmodule

ALUControl/tb_alu_control.v
`timescale 1ns / 1ps

// --------------------------------------------------
// Testbench: ALU Control
// Description: Verifies ALU Control logic based on 
//              ALUOp and funct values
// Author: [Your Name]
// Date: [Date]
// --------------------------------------------------

module tb_alu_control;

    // Testbench Signals
    reg [1:0] alu_op;
    reg [3:0] funct;
    wire [3:0] alu_control_out;

    // Instantiate the ALU Control Module
    alu_control uut (
        .alu_op(alu_op),
        .funct(funct),
        .alu_control_out(alu_control_out)
    );

    // Test Sequence
    initial begin
        // VCD Waveform Dump Setup
        $dumpfile("alu_control.vcd");  // Creates the waveform file
        $dumpvars(0, tb_alu_control);  // Dumps all signals

        // Test Case 1: Load/Store (Addition)
        alu_op = 2'b00; funct = 4'b0000; #10;
        $display("Load/Store: alu_op=%b, funct=%b -> alu_control_out=%b", alu_op, funct, alu_control_out);

        // Test Case 2: Branch (Subtraction)
        alu_op = 2'b01; funct = 4'b0000; #10;
        $display("Branch: alu_op=%b, funct=%b -> alu_control_out=%b", alu_op, funct, alu_control_out);

        // Test Case 3: R-Type ADD
        alu_op = 2'b10; funct = 4'b0000; #10;
        $display("R-Type ADD: alu_op=%b, funct=%b -> alu_control_out=%b", alu_op, funct, alu_control_out);

        // Test Case 4: R-Type SUB
        alu_op = 2'b10; funct = 4'b1000; #10;
        $display("R-Type SUB: alu_op=%b, funct=%b -> alu_control_out=%b", alu_op, funct, alu_control_out);

        // Test Case 5: R-Type AND
        alu_op = 2'b10; funct = 4'b0111; #10;
        $display("R-Type AND: alu_op=%b, funct=%b -> alu_control_out=%b", alu_op, funct, alu_control_out);

        // Test Case 6: R-Type OR
        alu_op = 2'b10; funct = 4'b0110; #10;
        $display("R-Type OR: alu_op=%b, funct=%b -> alu_control_out=%b", alu_op, funct, alu_control_out);

        // Test Case 7: R-Type XOR
        alu_op = 2'b10; funct = 4'b0100; #10;
        $display("R-Type XOR: alu_op=%b, funct=%b -> alu_control_out=%b", alu_op, funct, alu_control_out);

        // Test Case 8: Invalid Operation
        alu_op = 2'b10; funct = 4'b1111; #10;
        $display("Invalid: alu_op=%b, funct=%b -> alu_control_out=%b", alu_op, funct, alu_control_out);

        // End Simulation
        #20 $finish;
    end

endmodule

ALUControl/alu_control.vcd
$date
	Sun Feb 09 23:56:50 2025
$end
$version
	Icarus Verilog
$end
$timescale
	1ps
$end
$scope module tb_alu_control $end
$var wire 4 ! alu_control_out [3:0] $end
$var reg 2 " alu_op [1:0] $end
$var reg 4 # funct [3:0] $end
$scope module uut $end
$var wire 2 $ alu_op [1:0] $end
$var wire 4 % funct [3:0] $end
$var reg 4 & alu_control_out [3:0] $end
$upscope $end
$upscope $end
$enddefinitions $end
#0
$dumpvars
b10 &
b0 %
b0 $
b0 #
b0 "
b10 !
$end
#10000
b110 !
b110 &
b1 "
b1 $
#20000
b10 !
b10 &
b10 "
b10 $
#30000
b110 !
b110 &
b1000 #
b1000 %
#40000
b0 !
b0 &
b111 #
b111 %
#50000
b1 !
b1 &
b110 #
b110 %
#60000
b1100 !
b1100 &
b100 #
b100 %
#70000
b1111 !
b1111 &
b1111 #
b1111 %
