ImmediateGenerator/immediate_generator.v
`timescale 1ns / 1ps

// -----------------------------------------------
// Module: Immediate Generator
// Description: Extracts and sign-extends immediate values from instruction
// Author: [Your Name]
// Date: [Date]
// -----------------------------------------------

module immediate_generator (
    input wire [31:0] instruction,  // 32-bit instruction
    output reg [31:0] immediate     // Sign-extended immediate output
);

// Extracts the immediate field based on instruction format
always @(*) begin
    case (instruction[6:0])  // Check opcode field (bits 6:0)
        7'b0010011: // I-type (ADDI, ANDI, ORI, etc.)
            immediate = {{20{instruction[31]}}, instruction[31:20]};

        7'b0000011: // Load (LW, LB, LH, etc.)
            immediate = {{20{instruction[31]}}, instruction[31:20]};

        7'b0100011: // S-type (Store instructions SW, SB, SH)
            immediate = {{20{instruction[31]}}, instruction[31:25], instruction[11:7]};

        7'b1100011: // B-type (Branch instructions BEQ, BNE, etc.)
            immediate = {{19{instruction[31]}}, instruction[31], instruction[7], instruction[30:25], instruction[11:8], 1'b0};

        7'b1101111: // J-type (JAL)
            immediate = {{11{instruction[31]}}, instruction[31], instruction[19:12], instruction[20], instruction[30:21], 1'b0};

        7'b1100111: // I-type (JALR)
            immediate = {{20{instruction[31]}}, instruction[31:20]};

        7'b0110111, // U-type (LUI)
        7'b0010111: // U-type (AUIPC)
            immediate = {instruction[31:12], 12'b0}; // Upper immediate
        
        default: 
            immediate = 32'h00000000; // Default case for unknown instructions
    endcase
end

endmodule

ImmediateGenerator/tb_immediate_generator.v
`timescale 1ns / 1ps

module tb_immediate_generator;

    // Testbench Signals
    reg [31:0] instruction;
    wire [31:0] immediate;

    // Instantiate Immediate Generator
    immediate_generator uut (
        .instruction(instruction),
        .immediate(immediate)
    );

    // VCD Dump Setup
    initial begin
        $dumpfile("immediate_generator.vcd");
        $dumpvars(0, tb_immediate_generator);
    end

    // Test Sequence
    initial begin
        $monitor("Time=%0t | instruction=%h | immediate=%h", 
                 $time, instruction, immediate);
        
        // I-Type (ADDI)
        instruction = 32'b000000000000_00000_000_00000_0010011; #10;  // ADDI with immediate 0
        instruction = 32'b111111111111_00000_000_00000_0010011; #10;  // ADDI with immediate -1 (sign-extended)

        // Load Instruction (LW)
        instruction = 32'b000000000100_00000_010_00000_0000011; #10;  // LW with immediate 4

        // Store Instruction (SW)
        instruction = 32'b0000000_00001_00010_010_00011_0100011; #10; // SW with immediate 3
        
        // Branch Instruction (BEQ)
        instruction = 32'b0000000_00001_00010_000_0000001_1100011; #10; // BEQ with branch offset 1

        // JAL Instruction (J-Type)
        instruction = 32'b00000000000000000001_00000_1101111; #10;  // JAL with offset 1

        // JALR Instruction (I-Type)
        instruction = 32'b000000000101_00000_000_00000_1100111; #10;  // JALR with immediate 5

        // LUI Instruction (U-Type)
        instruction = 32'b00000000000000000000_00000_0110111; #10;  // LUI

        // AUIPC Instruction (U-Type)
        instruction = 32'b00000000000000000000_00000_0010111; #10;  // AUIPC
        
        #50 $finish;
    end

endmodule

ImmediateGenerator/immediate_generator.vcd
$date
	Sun Feb 09 23:26:47 2025
$end
$version
	Icarus Verilog
$end
$timescale
	1ps
$end
$scope module tb_immediate_generator $end
$var wire 32 ! immediate [31:0] $end
$var reg 32 " instruction [31:0] $end
$scope module uut $end
$var wire 32 # instruction [31:0] $end
$var reg 32 $ immediate [31:0] $end
$upscope $end
$upscope $end
$enddefinitions $end
#0
$dumpvars
b0 $
b10011 #
b10011 "
b0 !
$end
#10000
b11111111111111111111111111111111 !
b11111111111111111111111111111111 $
b11111111111100000000000000010011 "
b11111111111100000000000000010011 #
#20000
b100 !
b100 $
b10000000010000000000011 "
b10000000010000000000011 #
#30000
b11 !
b11 $
b100010010000110100011 "
b100010010000110100011 #
#40000
b100000000000 !
b100000000000 $
b10001000000000011100011 "
b10001000000000011100011 #
#50000
b1000000000000 !
b1000000000000 $
b1000001101111 "
b1000001101111 #
#60000
b101 !
b101 $
b10100000000000001100111 "
b10100000000000001100111 #
#70000
b0 !
b0 $
b110111 "
b110111 #
#80000
b10111 "
b10111 #
