ALU/alu.v
`timescale 1ns / 1ps

// -----------------------------------------------
// Module: Arithmetic Logic Unit (ALU)
// Description: Performs arithmetic and logical operations
// Author: [Your Name]
// Date: [Date]
// -----------------------------------------------

module alu (
    input wire [31:0] operand_a,  // First input operand
    input wire [31:0] operand_b,  // Second input operand
    input wire [3:0] alu_control, // Control signal for ALU operation
    output reg [31:0] alu_result, // Output result of the ALU
    output reg zero_flag          // Zero flag (1 if result is zero)
);

// ALU Operations (4-bit control encoding)
localparam ADD  = 4'b0000;  // Addition
localparam SUB  = 4'b0001;  // Subtraction
localparam AND  = 4'b0010;  // Bitwise AND
localparam OR   = 4'b0011;  // Bitwise OR
localparam XOR  = 4'b0100;  // Bitwise XOR
localparam SLL  = 4'b0101;  // Logical Shift Left
localparam SRL  = 4'b0110;  // Logical Shift Right
localparam SRA  = 4'b0111;  // Arithmetic Shift Right
localparam SLT  = 4'b1000;  // Set Less Than (signed)
localparam SLTU = 4'b1001;  // Set Less Than (unsigned)

// ALU Computation
always @(*) begin
    case (alu_control)
        ADD:  alu_result = operand_a + operand_b;
        SUB:  alu_result = operand_a - operand_b;
        AND:  alu_result = operand_a & operand_b;
        OR:   alu_result = operand_a | operand_b;
        XOR:  alu_result = operand_a ^ operand_b;
        SLL:  alu_result = operand_a << operand_b[4:0];  // Shift by lower 5 bits
        SRL:  alu_result = operand_a >> operand_b[4:0];
        SRA:  alu_result = $signed(operand_a) >>> operand_b[4:0]; // Arithmetic right shift
        SLT:  alu_result = ($signed(operand_a) < $signed(operand_b)) ? 32'b1 : 32'b0;
        SLTU: alu_result = (operand_a < operand_b) ? 32'b1 : 32'b0;
        default: alu_result = 32'h00000000;  // Default case (NOP)
    endcase
    // Set Zero Flag
    zero_flag = (alu_result == 32'h00000000) ? 1'b1 : 1'b0;
end

endmodule

ALU/tb_alu.v
`timescale 1ns / 1ps

module tb_alu;

    // Testbench Signals
    reg [31:0] operand_a;
    reg [31:0] operand_b;
    reg [3:0] alu_control;
    wire [31:0] alu_result;
    wire zero_flag;

    // Instantiate the ALU
    alu uut (
        .operand_a(operand_a),
        .operand_b(operand_b),
        .alu_control(alu_control),
        .alu_result(alu_result),
        .zero_flag(zero_flag)
    );

    // Test Sequence
    initial begin
        // VCD Waveform Dump Setup
        $dumpfile("alu_dump.vcd");  // Creates the waveform file
        $dumpvars(0, tb_alu);  // Dumps all signals
        
        // Test Cases
        operand_a = 32'h00000005;  operand_b = 32'h00000003;  alu_control = 4'b0000; #10; // ADD
        operand_a = 32'h00000005;  operand_b = 32'h00000003;  alu_control = 4'b0001; #10; // SUB
        operand_a = 32'hF0000000;  operand_b = 32'h00000001;  alu_control = 4'b0010; #10; // AND
        operand_a = 32'hF0000000;  operand_b = 32'h00000001;  alu_control = 4'b0011; #10; // OR
        operand_a = 32'h00000005;  operand_b = 32'h00000003;  alu_control = 4'b0100; #10; // XOR
        operand_a = 32'h00000001;  operand_b = 32'h00000002;  alu_control = 4'b0101; #10; // SLL
        operand_a = 32'h00000010;  operand_b = 32'h00000002;  alu_control = 4'b0110; #10; // SRL
        operand_a = 32'hF0000000;  operand_b = 32'h00000003;  alu_control = 4'b0111; #10; // SRA
        operand_a = 32'h00000005;  operand_b = 32'h0000000A;  alu_control = 4'b1000; #10; // SLT
        operand_a = 32'hFFFFFFFF;  operand_b = 32'h00000001;  alu_control = 4'b1001; #10; // SLTU
        
        #50 $finish;
    end

    // Monitor Output
    initial begin
        $monitor("Time=%0t | ALU Control=%b | A=%h | B=%h | Result=%h | Zero=%b", 
                 $time, alu_control, operand_a, operand_b, alu_result, zero_flag);
    end

endmodule

ALU/alu_dump.vcd
$date
	Sun Feb 09 23:47:09 2025
$end
$version
	Icarus Verilog
$end
$timescale
	1ps
$end
$scope module tb_alu $end
$var wire 1 ! zero_flag $end
$var wire 32 " alu_result [31:0] $end
$var reg 4 # alu_control [3:0] $end
$var reg 32 $ operand_a [31:0] $end
$var reg 32 % operand_b [31:0] $end
$scope module uut $end
$var wire 4 & alu_control [3:0] $end
$var wire 32 ' operand_a [31:0] $end
$var wire 32 ( operand_b [31:0] $end
$var reg 32 ) alu_result [31:0] $end
$var reg 1 ! zero_flag $end
$upscope $end
$upscope $end
$enddefinitions $end
#0
$dumpvars
b1000 )
b11 (
b101 '
b0 &
b11 %
b101 $
b0 #
b1000 "
0!
$end
#10000
b10 "
b10 )
b1 #
b1 &
#20000
1!
b0 "
b0 )
b10 #
b10 &
b1 %
b1 (
b11110000000000000000000000000000 $
b11110000000000000000000000000000 '
#30000
0!
b11110000000000000000000000000001 "
b11110000000000000000000000000001 )
b11 #
b11 &
#40000
b110 "
b110 )
b100 #
b100 &
b11 %
b11 (
b101 $
b101 '
#50000
b100 "
b100 )
b101 #
b101 &
b10 %
b10 (
b1 $
b1 '
#60000
b110 #
b110 &
b10000 $
b10000 '
#70000
b11111110000000000000000000000000 "
b11111110000000000000000000000000 )
b111 #
b111 &
b11 %
b11 (
b11110000000000000000000000000000 $
b11110000000000000000000000000000 '
#80000
b1 "
b1 )
b1000 #
b1000 &
b1010 %
b1010 (
b101 $
b101 '
#90000
1!
b0 "
b0 )
b1001 #
b1001 &
b1 %
b1 (
b11111111111111111111111111111111 $
b11111111111111111111111111111111 '
